android_use/__init__.py
android_use/app.py
android_use/cli.py
android_use/config.py
android_use/encryption.py
android_use/logging_config.py
android_use/utils.py
android_use/agent/__init__.py
android_use/agent/gif.py
android_use/agent/message_manager.py
android_use/agent/prompts.py
android_use/agent/service.py
android_use/agent/views.py
android_use/android/__init__.py
android_use/android/context.py
android_use/android/views.py
android_use/llm/__init__.py
android_use/llm/base.py
android_use/llm/exceptions.py
android_use/llm/messages.py
android_use/llm/models.py
android_use/llm/schema.py
android_use/llm/views.py
android_use/llm/anthropic/chat.py
android_use/llm/anthropic/serializer.py
android_use/llm/aws/__init__.py
android_use/llm/aws/chat_anthropic.py
android_use/llm/aws/chat_bedrock.py
android_use/llm/aws/serializer.py
android_use/llm/azure/chat.py
android_use/llm/cerebras/chat.py
android_use/llm/cerebras/serializer.py
android_use/llm/deepseek/chat.py
android_use/llm/deepseek/serializer.py
android_use/llm/google/__init__.py
android_use/llm/google/chat.py
android_use/llm/google/serializer.py
android_use/llm/groq/chat.py
android_use/llm/groq/parser.py
android_use/llm/groq/serializer.py
android_use/llm/mistral/__init__.py
android_use/llm/mistral/chat.py
android_use/llm/mistral/schema.py
android_use/llm/oci_raw/__init__.py
android_use/llm/oci_raw/chat.py
android_use/llm/oci_raw/serializer.py
android_use/llm/ollama/chat.py
android_use/llm/ollama/serializer.py
android_use/llm/openai/chat.py
android_use/llm/openai/like.py
android_use/llm/openai/serializer.py
android_use/llm/openai_compatible/chat.py
android_use/llm/openrouter/chat.py
android_use/llm/openrouter/serializer.py
android_use/llm/vercel/__init__.py
android_use/llm/vercel/chat.py
android_use/llm/vercel/serializer.py
android_use/tokens/__init__.py
android_use/tokens/mappings.py
android_use/tokens/service.py
android_use/tokens/views.py
android_use/tools/__init__.py
android_use/tools/action_highlight.py
android_use-0.1.7.dist-info/licenses/LICENSE
android_use-0.1.7.dist-info/METADATA
android_use-0.1.7.dist-info/WHEEL
android_use-0.1.7.dist-info/entry_points.txt
android_use-0.1.7.dist-info/top_level.txt
android_use-0.1.7.dist-info/RECORD
