Metadata-Version: 2.4
Name: android-use
Version: 0.1.7
Summary: Make android accessible for AI agents
Requires-Python: >=3.11
License-File: LICENSE
Requires-Dist: uiautomator2>=3.2.9
Requires-Dist: rich>=14.0.0
Requires-Dist: google-api-core>=2.25.0
Requires-Dist: httpx>=0.28.1
Requires-Dist: portalocker<3.0.0,>=2.7.0
Requires-Dist: posthog>=3.7.0
Requires-Dist: psutil>=7.0.0
Requires-Dist: pydantic>=2.11.5
Requires-Dist: pyobjc>=11.0; platform_system == "darwin"
Requires-Dist: python-dotenv>=1.0.1
Requires-Dist: requests>=2.32.3
Requires-Dist: screeninfo>=0.8.1; platform_system != "darwin"
Requires-Dist: typing-extensions>=4.12.2
Requires-Dist: uuid7>=0.1.0
Requires-Dist: authlib>=1.6.0
Requires-Dist: google-genai<2.0.0,>=1.50.0
Requires-Dist: openai<3.0.0,>=2.7.2
Requires-Dist: anthropic<1.0.0,>=0.72.1
Requires-Dist: groq>=0.30.0
Requires-Dist: ollama>=0.5.1
Requires-Dist: google-api-python-client>=2.174.0
Requires-Dist: google-auth>=2.40.3
Requires-Dist: google-auth-oauthlib>=1.2.2
Requires-Dist: mcp>=1.10.1
Requires-Dist: pypdf>=5.7.0
Requires-Dist: python-dotenv>=1.0.1
Requires-Dist: gradio>=5.23.3
Requires-Dist: apkutils2>=1.0.0
Requires-Dist: json-repair>=0.54.3
Requires-Dist: getmac>=0.9.5
Requires-Dist: scikit-image==0.26.0
Dynamic: license-file
